Workbook

Sheet Executive_Summary
A1: CMS synthetic claims - not real patient or provider performance.
A2: Executive summary
A3: Data: CMS DE-SynPUF sample 1, retrieved per data/data_manifest.json. Definitions: see Metric_Dictionary. Rates are formulas; the Pipeline columns hold the warehouse values they must equal.
A4: Year | B4: Beneficiaries | C4: Member_years | D4: Claims | E4: Paid_amount | F4: Admissions | G4: ED_proxy_visits | H4: Readmission_eligible | I4: Readmission_events | J4: Top5_paid_amount | K4: Pipeline_admissions_per_1000 | L4: Pipeline_readmission_proxy | M4: Pipeline_top5_share | N4: Paid_per_beneficiary | O4: Admissions_per_1000_member_years | P4: ED_proxy_per_1000_member_years | Q4: Readmission_proxy | R4: Top5_payment_share | S4: Check_vs_pipeline
A5: 2008 | B5: 116352 | C5: 107296.75 | D5: 2025978 | E5: 483275670 | F5: 26262 | G5: 22494 | H5: 25861 | I5: 3906 | J5: 234226340 | K5: 244.76044 | L5: 0.15103824 | M5: 0.48466404 | N5: =IF(B5>0,E5/B5,"") | O5: =IF(C5>0,F5/C5*1000,"") | P5: =IF(C5>0,G5/C5*1000,"") | Q5: =IF(H5>0,I5/H5,"") | R5: =IF(E5<>0,J5/E5,"") | S5: =IF(AND(ABS(O5-K5)<0.000001,ABS(R5-M5)<0.000001),"OK","CHECK")
A6: 2009 | B6: 114538 | C6: 106352.17 | D6: 2210561 | E6: 504801500 | F6: 24710 | G6: 26334 | H6: 24763 | I6: 1866 | J6: 197944970 | K6: 232.34129 | L6: 0.075354359 | M6: 0.39212437 | N6: =IF(B6>0,E6/B6,"") | O6: =IF(C6>0,F6/C6*1000,"") | P6: =IF(C6>0,G6/C6*1000,"") | Q6: =IF(H6>0,I6/H6,"") | R6: =IF(E6<>0,J6/E6,"") | S6: =IF(AND(ABS(O6-K6)<0.000001,ABS(R6-M6)<0.000001),"OK","CHECK")
A7: 2010 | B7: 112754 | C7: 104407.42 | D7: 1350500 | E7: 286712060 | F7: 13387 | G7: 13753 | H7: 13421 | I7: 577 | J7: 123536500 | K7: 128.21886 | L7: 0.042992325 | M7: 0.43087305 | N7: =IF(B7>0,E7/B7,"") | O7: =IF(C7>0,F7/C7*1000,"") | P7: =IF(C7>0,G7/C7*1000,"") | Q7: =IF(H7>0,I7/H7,"") | R7: =IF(E7<>0,J7/E7,"") | S7: =IF(AND(ABS(O7-K7)<0.000001,ABS(R7-M7)<0.000001),"OK","CHECK")
A10: Limitations
A11: What this workbook is: an operations review of CMS DE-SynPUF synthetic Medicare claims. It demonstrates a pipeline; it does not describe real Medicare.
A12: Not included: prescription drug events; any beneficiary-level rows; any claim of savings, fraud, or provider quality.
A13: Utilization risk tier is a transparent descriptive stratification, not CMS-HCC or any official risk adjustment.
A14: The 30-day readmission proxy is measure-inspired, not a certified measure. 2010 volumes are lower in the source, so year-to-year trends are not interpretable.

Sheet Monthly_Utilization
A1: CMS synthetic claims - not real patient or provider performance.
A2: Monthly utilization by care setting
A3: Claims per 1,000 members is a formula: claims / members x 1,000.
A4: Year_month | B4: Year | C4: Setting | D4: Members | E4: Claims | F4: Unique_beneficiaries | G4: Admissions | H4: ED_proxy_visits | I4: Outpatient_visits | J4: Carrier_service_lines | K4: Claims_per_1000_members
A5: 2008-01 | B5: 2008 | C5: carrier | D5: 111058 | E5: 65385 | F5: 28267 | J5: 127405 | K5: =IF(D5>0,E5/D5*1000,"")
A6: 2008-01 | B6: 2008 | C6: inpatient | D6: 111058 | E6: 1533 | F6: 1371 | G6: 1454 | K6: =IF(D6>0,E6/D6*1000,"")
A7: 2008-01 | B7: 2008 | C7: outpatient | D7: 111058 | E7: 10256 | F7: 8181 | H7: 796 | I7: 10256 | K7: =IF(D7>0,E7/D7*1000,"")
A8: 2008-02 | B8: 2008 | C8: carrier | D8: 110398 | E8: 102838 | F8: 41621 | J8: 200157 | K8: =IF(D8>0,E8/D8*1000,"")
A9: 2008-02 | B9: 2008 | C9: inpatient | D9: 110398 | E9: 1805 | F9: 1594 | G9: 1680 | K9: =IF(D9>0,E9/D9*1000,"")
A10: 2008-02 | B10: 2008 | C10: outpatient | D10: 110398 | E10: 15383 | F10: 11941 | H10: 1238 | I10: 15383 | K10: =IF(D10>0,E10/D10*1000,"")
A11: 2008-03 | B11: 2008 | C11: carrier | D11: 109809 | E11: 135921 | F11: 52408 | J11: 264760 | K11: =IF(D11>0,E11/D11*1000,"")
A12: 2008-03 | B12: 2008 | C12: inpatient | D12: 109809 | E12: 2300 | F12: 2076 | G12: 2161 | K12: =IF(D12>0,E12/D12*1000,"")
A13: 2008-03 | B13: 2008 | C13: outpatient | D13: 109809 | E13: 21051 | F13: 16046 | H13: 1707 | I13: 21051 | K13: =IF(D13>0,E13/D13*1000,"")
A14: 2008-04 | B14: 2008 | C14: carrier | D14: 109187 | E14: 146516 | F14: 56501 | J14: 285042 | K14: =IF(D14>0,E14/D14*1000,"")
A15: 2008-04 | B15: 2008 | C15: inpatient | D15: 109187 | E15: 2320 | F15: 2082 | G15: 2196 | K15: =IF(D15>0,E15/D15*1000,"")
A16: 2008-04 | B16: 2008 | C16: outpatient | D16: 109187 | E16: 23164 | F16: 17534 | H16: 1852 | I16: 23164 | K16: =IF(D16>0,E16/D16*1000,"")
A17: 2008-05 | B17: 2008 | C17: carrier | D17: 108578 | E17: 154711 | F17: 58937 | J17: 302802 | K17: =IF(D17>0,E17/D17*1000,"")
A18: 2008-05 | B18: 2008 | C18: inpatient | D18: 108578 | E18: 2585 | F18: 2268 | G18: 2420 | K18: =IF(D18>0,E18/D18*1000,"")
A19: 2008-05 | B19: 2008 | C19: outpatient | D19: 108578 | E19: 24918 | F19: 18786 | H19: 1924 | I19: 24918 | K19: =IF(D19>0,E19/D19*1000,"")
A20: 2008-06 | B20: 2008 | C20: carrier | D20: 107859 | E20: 152202 | F20: 59323 | J20: 297309 | K20: =IF(D20>0,E20/D20*1000,"")
A21: 2008-06 | B21: 2008 | C21: inpatient | D21: 107859 | E21: 2455 | F21: 2194 | G21: 2303 | K21: =IF(D21>0,E21/D21*1000,"")
A22: 2008-06 | B22: 2008 | C22: outpatient | D22: 107859 | E22: 25063 | F22: 19105 | H22: 1961 | I22: 25063 | K22: =IF(D22>0,E22/D22*1000,"")
A23: 2008-07 | B23: 2008 | C23: carrier | D23: 107171 | E23: 159898 | F23: 61091 | J23: 314742 | K23: =IF(D23>0,E23/D23*1000,"")
A24: 2008-07 | B24: 2008 | C24: inpatient | D24: 107171 | E24: 2467 | F24: 2233 | G24: 2342 | K24: =IF(D24>0,E24/D24*1000,"")
A25: 2008-07 | B25: 2008 | C25: outpatient | D25: 107171 | E25: 26414 | F25: 19968 | H25: 2024 | I25: 26414 | K25: =IF(D25>0,E25/D25*1000,"")
A26: 2008-08 | B26: 2008 | C26: carrier | D26: 106412 | E26: 160504 | F26: 61934 | J26: 313086 | K26: =IF(D26>0,E26/D26*1000,"")
A27: 2008-08 | B27: 2008 | C27: inpatient | D27: 106412 | E27: 2586 | F27: 2330 | G27: 2469 | K27: =IF(D27>0,E27/D27*1000,"")
A28: 2008-08 | B28: 2008 | C28: outpatient | D28: 106412 | E28: 27203 | F28: 20675 | H28: 2151 | I28: 27203 | K28: =IF(D28>0,E28/D28*1000,"")
A29: 2008-09 | B29: 2008 | C29: carrier | D29: 105655 | E29: 157037 | F29: 62000 | J29: 307921 | K29: =IF(D29>0,E29/D29*1000,"")
A30: 2008-09 | B30: 2008 | C30: inpatient | D30: 105655 | E30: 2454 | F30: 2257 | G30: 2347 | K30: =IF(D30>0,E30/D30*1000,"")
A31: 2008-09 | B31: 2008 | C31: outpatient | D31: 105655 | E31: 26418 | F31: 20264 | H31: 2170 | I31: 26418 | K31: =IF(D31>0,E31/D31*1000,"")
A32: 2008-10 | B32: 2008 | C32: carrier | D32: 104778 | E32: 161664 | F32: 62798 | J32: 317590 | K32: =IF(D32>0,E32/D32*1000,"")
A33: 2008-10 | B33: 2008 | C33: inpatient | D33: 104778 | E33: 2506 | F33: 2290 | G33: 2397 | K33: =IF(D33>0,E33/D33*1000,"")
A34: 2008-10 | B34: 2008 | C34: outpatient | D34: 104778 | E34: 27482 | F34: 20935 | H34: 2151 | I34: 27482 | K34: =IF(D34>0,E34/D34*1000,"")
A35: 2008-11 | B35: 2008 | C35: carrier | D35: 103848 | E35: 156810 | F35: 62327 | J35: 306947 | K35: =IF(D35>0,E35/D35*1000,"")
A36: 2008-11 | B36: 2008 | C36: inpatient | D36: 103848 | E36: 2341 | F36: 2161 | G36: 2241 | K36: =IF(D36>0,E36/D36*1000,"")
A37: 2008-11 | B37: 2008 | C37: outpatient | D37: 103848 | E37: 27104 | F37: 20973 | H37: 2165 | I37: 27104 | K37: =IF(D37>0,E37/D37*1000,"")
A38: 2008-12 | B38: 2008 | C38: carrier | D38: 102808 | E38: 161916 | F38: 63155 | J38: 319601 | K38: =IF(D38>0,E38/D38*1000,"")
A39: 2008-12 | B39: 2008 | C39: inpatient | D39: 102808 | E39: 2328 | F39: 2168 | G39: 2252 | K39: =IF(D39>0,E39/D39*1000,"")
A40: 2008-12 | B40: 2008 | C40: outpatient | D40: 102808 | E40: 28440 | F40: 21752 | H40: 2355 | I40: 28440 | K40: =IF(D40>0,E40/D40*1000,"")
A41: 2009-01 | B41: 2009 | C41: carrier | D41: 107297 | E41: 161275 | F41: 63349 | J41: 319707 | K41: =IF(D41>0,E41/D41*1000,"")
A42: 2009-01 | B42: 2009 | C42: inpatient | D42: 107297 | E42: 2331 | F42: 2188 | G42: 2262 | K42: =IF(D42>0,E42/D42*1000,"")
A43: 2009-01 | B43: 2009 | C43: outpatient | D43: 107297 | E43: 28633 | F43: 21895 | H43: 2283 | I43: 28633 | K43: =IF(D43>0,E43/D43*1000,"")
A44: 2009-02 | B44: 2009 | C44: carrier | D44: 107105 | E44: 145547 | F44: 61029 | J44: 286995 | K44: =IF(D44>0,E44/D44*1000,"")
A45: 2009-02 | B45: 2009 | C45: inpatient | D45: 107105 | E45: 2014 | F45: 1912 | G45: 1963 | K45: =IF(D45>0,E45/D45*1000,"")
A46: 2009-02 | B46: 2009 | C46: outpatient | D46: 107105 | E46: 25970 | F46: 20417 | H46: 2157 | I46: 25970 | K46: =IF(D46>0,E46/D46*1000,"")
A47: 2009-03 | B47: 2009 | C47: carrier | D47: 106934 | E47: 160601 | F47: 63440 | J47: 318757 | K47: =IF(D47>0,E47/D47*1000,"")
A48: 2009-03 | B48: 2009 | C48: inpatient | D48: 106934 | E48: 2216 | F48: 2121 | G48: 2172 | K48: =IF(D48>0,E48/D48*1000,"")
A49: 2009-03 | B49: 2009 | C49: outpatient | D49: 106934 | E49: 28509 | F49: 22038 | H49: 2346 | I49: 28509 | K49: =IF(D49>0,E49/D49*1000,"")
A50: 2009-04 | B50: 2009 | C50: carrier | D50: 106774 | E50: 155798 | F50: 63019 | J50: 309709 | K50: =IF(D50>0,E50/D50*1000,"")
A51: 2009-04 | B51: 2009 | C51: inpatient | D51: 106774 | E51: 2184 | F51: 2086 | G51: 2135 | K51: =IF(D51>0,E51/D51*1000,"")
A52: 2009-04 | B52: 2009 | C52: outpatient | D52: 106774 | E52: 27813 | F52: 21541 | H52: 2283 | I52: 27813 | K52: =IF(D52>0,E52/D52*1000,"")
A53: 2009-05 | B53: 2009 | C53: carrier | D53: 106609 | E53: 160508 | F53: 63642 | J53: 319934 | K53: =IF(D53>0,E53/D53*1000,"")
A54: 2009-05 | B54: 2009 | C54: inpatient | D54: 106609 | E54: 2215 | F54: 2120 | G54: 2171 | K54: =IF(D54>0,E54/D54*1000,"")
A55: 2009-05 | B55: 2009 | C55: outpatient | D55: 106609 | E55: 28405 | F55: 22063 | H55: 2291 | I55: 28405 | K55: =IF(D55>0,E55/D55*1000,"")
A56: 2009-06 | B56: 2009 | C56: carrier | D56: 106440 | E56: 154693 | F56: 62880 | J56: 308630 | K56: =IF(D56>0,E56/D56*1000,"")
A57: 2009-06 | B57: 2009 | C57: inpatient | D57: 106440 | E57: 2117 | F57: 2030 | G57: 2073 | K57: =IF(D57>0,E57/D57*1000,"")
A58: 2009-06 | B58: 2009 | C58: outpatient | D58: 106440 | E58: 27392 | F58: 21435 | H58: 2210 | I58: 27392 | K58: =IF(D58>0,E58/D58*1000,"")
A59: 2009-07 | B59: 2009 | C59: carrier | D59: 106267 | E59: 159153 | F59: 63623 | J59: 317537 | K59: =IF(D59>0,E59/D59*1000,"")
A60: 2009-07 | B60: 2009 | C60: inpatient | D60: 106267 | E60: 2086 | F60: 2010 | G60: 2046 | K60: =IF(D60>0,E60/D60*1000,"")
A61: 2009-07 | B61: 2009 | C61: outpatient | D61: 106267 | E61: 27717 | F61: 21515 | H61: 2324 | I61: 27717 | K61: =IF(D61>0,E61/D61*1000,"")
A62: 2009-08 | B62: 2009 | C62: carrier | D62: 106107 | E62: 157974 | F62: 63525 | J62: 315047 | K62: =IF(D62>0,E62/D62*1000,"")
A63: 2009-08 | B63: 2009 | C63: inpatient | D63: 106107 | E63: 2138 | F63: 2046 | G63: 2106 | K63: =IF(D63>0,E63/D63*1000,"")
A64: 2009-08 | B64: 2009 | C64: outpatient | D64: 106107 | E64: 27641 | F64: 21434 | H64: 2232 | I64: 27641 | K64: =IF(D64>0,E64/D64*1000,"")
A65: 2009-09 | B65: 2009 | C65: carrier | D65: 105940 | E65: 151797 | F65: 62562 | J65: 302746 | K65: =IF(D65>0,E65/D65*1000,"")
A66: 2009-09 | B66: 2009 | C66: inpatient | D66: 105940 | E66: 2126 | F66: 2023 | G66: 2076 | K66: =IF(D66>0,E66/D66*1000,"")
A67: 2009-09 | B67: 2009 | C67: outpatient | D67: 105940 | E67: 26050 | F67: 20497 | H67: 2172 | I67: 26050 | K67: =IF(D67>0,E67/D67*1000,"")
A68: 2009-10 | B68: 2009 | C68: carrier | D68: 105765 | E68: 155679 | F68: 63145 | J68: 310929 | K68: =IF(D68>0,E68/D68*1000,"")
A69: 2009-10 | B69: 2009 | C69: inpatient | D69: 105765 | E69: 2006 | F69: 1937 | G69: 1974 | K69: =IF(D69>0,E69/D69*1000,"")
A70: 2009-10 | B70: 2009 | C70: outpatient | D70: 105765 | E70: 26016 | F70: 20352 | H70: 2117 | I70: 26016 | K70: =IF(D70>0,E70/D70*1000,"")
A71: 2009-11 | B71: 2009 | C71: carrier | D71: 105585 | E71: 148836 | F71: 62043 | J71: 298162 | K71: =IF(D71>0,E71/D71*1000,"")
A72: 2009-11 | B72: 2009 | C72: inpatient | D72: 105585 | E72: 1901 | F72: 1836 | G72: 1867 | K72: =IF(D72>0,E72/D72*1000,"")
A73: 2009-11 | B73: 2009 | C73: outpatient | D73: 105585 | E73: 24322 | F73: 19196 | H73: 2016 | I73: 24322 | K73: =IF(D73>0,E73/D73*1000,"")
A74: 2009-12 | B74: 2009 | C74: carrier | D74: 105403 | E74: 151112 | F74: 62237 | J74: 301431 | K74: =IF(D74>0,E74/D74*1000,"")
A75: 2009-12 | B75: 2009 | C75: inpatient | D75: 105403 | E75: 1896 | F75: 1834 | G75: 1865 | K75: =IF(D75>0,E75/D75*1000,"")
A76: 2009-12 | B76: 2009 | C76: outpatient | D76: 105403 | E76: 23890 | F76: 18910 | H76: 1903 | I76: 23890 | K76: =IF(D76>0,E76/D76*1000,"")
A77: 2010-01 | B77: 2010 | C77: carrier | D77: 106435 | E77: 148270 | F77: 61170 | J77: 296713 | K77: =IF(D77>0,E77/D77*1000,"")
A78: 2010-01 | B78: 2010 | C78: inpatient | D78: 106435 | E78: 1786 | F78: 1720 | G78: 1761 | K78: =IF(D78>0,E78/D78*1000,"")
A79: 2010-01 | B79: 2010 | C79: outpatient | D79: 106435 | E79: 22594 | F79: 17890 | H79: 1740 | I79: 22594 | K79: =IF(D79>0,E79/D79*1000,"")
A80: 2010-02 | B80: 2010 | C80: carrier | D80: 106126 | E80: 129653 | F80: 57454 | J80: 258106 | K80: =IF(D80>0,E80/D80*1000,"")
A81: 2010-02 | B81: 2010 | C81: inpatient | D81: 106126 | E81: 1533 | F81: 1495 | G81: 1502 | K81: =IF(D81>0,E81/D81*1000,"")
A82: 2010-02 | B82: 2010 | C82: outpatient | D82: 106126 | E82: 19264 | F82: 15625 | H82: 1600 | I82: 19264 | K82: =IF(D82>0,E82/D82*1000,"")
A83: 2010-03 | B83: 2010 | C83: carrier | D83: 105875 | E83: 137200 | F83: 57821 | J83: 273465 | K83: =IF(D83>0,E83/D83*1000,"")
A84: 2010-03 | B84: 2010 | C84: inpatient | D84: 105875 | E84: 1553 | F84: 1509 | G84: 1532 | K84: =IF(D84>0,E84/D84*1000,"")
A85: 2010-03 | B85: 2010 | C85: outpatient | D85: 105875 | E85: 20157 | F85: 16106 | H85: 1627 | I85: 20157 | K85: =IF(D85>0,E85/D85*1000,"")
A86: 2010-04 | B86: 2010 | C86: carrier | D86: 105570 | E86: 125580 | F86: 54545 | J86: 251058 | K86: =IF(D86>0,E86/D86*1000,"")
A87: 2010-04 | B87: 2010 | C87: inpatient | D87: 105570 | E87: 1481 | F87: 1430 | G87: 1458 | K87: =IF(D87>0,E87/D87*1000,"")
A88: 2010-04 | B88: 2010 | C88: outpatient | D88: 105570 | E88: 18017 | F88: 14553 | H88: 1428 | I88: 18017 | K88: =IF(D88>0,E88/D88*1000,"")
A89: 2010-05 | B89: 2010 | C89: carrier | D89: 105215 | E89: 120031 | F89: 52078 | J89: 240285 | K89: =IF(D89>0,E89/D89*1000,"")
A90: 2010-05 | B90: 2010 | C90: inpatient | D90: 105215 | E90: 1445 | F90: 1401 | G90: 1423 | K90: =IF(D90>0,E90/D90*1000,"")
A91: 2010-05 | B91: 2010 | C91: outpatient | D91: 105215 | E91: 17193 | F91: 13839 | H91: 1363 | I91: 17193 | K91: =IF(D91>0,E91/D91*1000,"")
A92: 2010-06 | B92: 2010 | C92: carrier | D92: 104821 | E92: 105292 | F92: 47468 | J92: 210614 | K92: =IF(D92>0,E92/D92*1000,"")
A93: 2010-06 | B93: 2010 | C93: inpatient | D93: 104821 | E93: 1312 | F93: 1276 | G93: 1291 | K93: =IF(D93>0,E93/D93*1000,"")
A94: 2010-06 | B94: 2010 | C94: outpatient | D94: 104821 | E94: 15097 | F94: 12356 | H94: 1153 | I94: 15097 | K94: =IF(D94>0,E94/D94*1000,"")
A95: 2010-07 | B95: 2010 | C95: carrier | D95: 104410 | E95: 97062 | F95: 43691 | J95: 193821 | K95: =IF(D95>0,E95/D95*1000,"")
A96: 2010-07 | B96: 2010 | C96: inpatient | D96: 104410 | E96: 1199 | F96: 1169 | G96: 1187 | K96: =IF(D96>0,E96/D96*1000,"")
A97: 2010-07 | B97: 2010 | C97: outpatient | D97: 104410 | E97: 14193 | F97: 11504 | H97: 1091 | I97: 14193 | K97: =IF(D97>0,E97/D97*1000,"")
A98: 2010-08 | B98: 2010 | C98: carrier | D98: 103979 | E98: 84096 | F98: 38789 | J98: 168472 | K98: =IF(D98>0,E98/D98*1000,"")
A99: 2010-08 | B99: 2010 | C99: inpatient | D99: 103979 | E99: 1068 | F99: 1051 | G99: 1058 | K99: =IF(D99>0,E99/D99*1000,"")
A100: 2010-08 | B100: 2010 | C100: outpatient | D100: 103979 | E100: 12443 | F100: 10159 | H100: 955 | I100: 12443 | K100: =IF(D100>0,E100/D100*1000,"")
...

Sheet Monthly_Payments
A1: CMS synthetic claims - not real patient or provider performance.
A2: Monthly payments by care setting
A3: Payment fields keep their CMS names; negative amounts are payment adjustments and are included.
A4: Year_month | B4: Year | C4: Setting | D4: Payment_source_field | E4: Claims | F4: Payment_amount | G4: Negative_payment_claims | H4: Zero_payment_claims | I4: Payment_per_claim
A5: 2008-01 | B5: 2008 | C5: carrier | D5: LINE_NCH_PMT_AMT_1..13 (sum of lines) | E5: 65385 | F5: 5504620 | G5: 0 | H5: 7131 | I5: =IF(E5>0,F5/E5,"")
A6: 2008-01 | B6: 2008 | C6: inpatient | D6: CLM_PMT_AMT (sum of segments) | E6: 1533 | F6: 14466480 | G6: 1 | H6: 54 | I6: =IF(E6>0,F6/E6,"")
A7: 2008-01 | B7: 2008 | C7: outpatient | D7: CLM_PMT_AMT (sum of segments) | E7: 10256 | F7: 3064860 | G7: 37 | H7: 430 | I7: =IF(E7>0,F7/E7,"")
A8: 2008-02 | B8: 2008 | C8: carrier | D8: LINE_NCH_PMT_AMT_1..13 (sum of lines) | E8: 102838 | F8: 8595400 | G8: 0 | H8: 11131 | I8: =IF(E8>0,F8/E8,"")
A9: 2008-02 | B9: 2008 | C9: inpatient | D9: CLM_PMT_AMT (sum of segments) | E9: 1805 | F9: 16289110 | G9: 0 | H9: 81 | I9: =IF(E9>0,F9/E9,"")
A10: 2008-02 | B10: 2008 | C10: outpatient | D10: CLM_PMT_AMT (sum of segments) | E10: 15383 | F10: 4480900 | G10: 40 | H10: 629 | I10: =IF(E10>0,F10/E10,"")
A11: 2008-03 | B11: 2008 | C11: carrier | D11: LINE_NCH_PMT_AMT_1..13 (sum of lines) | E11: 135921 | F11: 11396260 | G11: 0 | H11: 14838 | I11: =IF(E11>0,F11/E11,"")
A12: 2008-03 | B12: 2008 | C12: inpatient | D12: CLM_PMT_AMT (sum of segments) | E12: 2300 | F12: 20901530 | G12: 2 | H12: 92 | I12: =IF(E12>0,F12/E12,"")
A13: 2008-03 | B13: 2008 | C13: outpatient | D13: CLM_PMT_AMT (sum of segments) | E13: 21051 | F13: 5619130 | G13: 76 | H13: 839 | I13: =IF(E13>0,F13/E13,"")
A14: 2008-04 | B14: 2008 | C14: carrier | D14: LINE_NCH_PMT_AMT_1..13 (sum of lines) | E14: 146516 | F14: 12258090 | G14: 0 | H14: 15929 | I14: =IF(E14>0,F14/E14,"")
A15: 2008-04 | B15: 2008 | C15: inpatient | D15: CLM_PMT_AMT (sum of segments) | E15: 2320 | F15: 21728870 | G15: 3 | H15: 82 | I15: =IF(E15>0,F15/E15,"")
A16: 2008-04 | B16: 2008 | C16: outpatient | D16: CLM_PMT_AMT (sum of segments) | E16: 23164 | F16: 6427460 | G16: 79 | H16: 949 | I16: =IF(E16>0,F16/E16,"")
... A112: 2010-12 | B112: 2010 | C112: outpatient | D112: CLM_PMT_AMT (sum of segments) | E112: 6812 | F112: 1780490 | G112: 23 | H112: 239 | I112: =IF(E112>0,F112/E112,"")

Sheet Provider_Review
A1: CMS synthetic claims - not real patient or provider performance.
A2: Provider review list (SYNTHETIC flags only)
A3: Review flags are prompts to compare peers. They are not fraud, quality or performance findings. Provider IDs are synthetic.
A4: Year | B4: Provider_type | C4: Provider_id | D4: Claims | E4: Beneficiaries | F4: Payment_amount | G4: Peer_count | H4: Review_flag | I4: Reason_codes | J4: Payment_per_claim
A5: 2008 | B5: facility_inpatient | C5: 23006G | D5: 315 | E5: 239 | F5: 2897100 | G5: 2408 | H5: REVIEW | I5: HIGH_CLAIM_VOLUME | J5: =IF(D5>0,F5/D5,"")
A6: 2008 | B6: facility_inpatient | C6: 3600NG | D6: 228 | E6: 147 | F6: 2373900 | G6: 2408 | H6: REVIEW | I6: HIGH_CLAIM_VOLUME | J6: =IF(D6>0,F6/D6,"")
A7: 2008 | B7: facility_inpatient | C7: 1000AH | D7: 237 | E7: 212 | F7: 2319700 | G7: 2408 | H7: REVIEW | I7: HIGH_CLAIM_VOLUME | J7: =IF(D7>0,F7/D7,"")
A8: 2008 | B8: facility_inpatient | C8: 2100WC | D8: 167 | E8: 145 | F8: 1761000 | G8: 2408 | H8: REVIEW | I8: HIGH_CLAIM_VOLUME | J8: =IF(D8>0,F8/D8,"")
A9: 2008 | B9: facility_inpatient | C9: 3100JN | D9: 136 | E9: 100 | F9: 1619900 | G9: 2408 | H9: REVIEW | I9: HIGH_CLAIM_VOLUME | J9: =IF(D9>0,F9/D9,"")
A10: 2008 | B10: facility_inpatient | C10: 3400XN | D10: 162 | E10: 120 | F10: 1578000 | G10: 2408 | H10: REVIEW | I10: HIGH_CLAIM_VOLUME | J10: =IF(D10>0,F10/D10,"")
A11: 2008 | B11: facility_inpatient | C11: 4500DP | D11: 154 | E11: 104 | F11: 1520400 | G11: 2408 | H11: REVIEW | I11: HIGH_CLAIM_VOLUME | J11: =IF(D11>0,F11/D11,"")
A12: 2008 | B12: facility_inpatient | C12: 1401RR | D12: 181 | E12: 150 | F12: 1506900 | G12: 2408 | H12: REVIEW | I12: HIGH_CLAIM_VOLUME | J12: =IF(D12>0,F12/D12,"")
A13: 2008 | B13: facility_inpatient | C13: 1002DC | D13: 134 | E13: 105 | F13: 1501100 | G13: 2408 | H13: REVIEW | I13: HIGH_CLAIM_VOLUME | J13: =IF(D13>0,F13/D13,"")
A14: 2008 | B14: facility_inpatient | C14: 2600ZT | D14: 165 | E14: 132 | F14: 1487450 | G14: 2408 | H14: REVIEW | I14: HIGH_CLAIM_VOLUME | J14: =IF(D14>0,F14/D14,"")
A15: 2008 | B15: facility_inpatient | C15: 0501MA | D15: 126 | E15: 112 | F15: 1396200 | G15: 2408 | H15: REVIEW | I15: HIGH_CLAIM_VOLUME | J15: =IF(D15>0,F15/D15,"")
A16: 2008 | B16: facility_inpatient | C16: 0400AC | D16: 130 | E16: 85 | F16: 1377000 | G16: 2408 | H16: REVIEW | I16: HIGH_CLAIM_VOLUME | J16: =IF(D16>0,F16/D16,"")
... A1198: 2010 | B1198: facility_inpatient | C1198: 4900CN | D1198: 43 | E1198: 41 | F1198: 453000 | G1198: 2063 | H1198: REVIEW | I1198: HIGH_CLAIM_VOLUME | J1198: =IF(D1198>0,F1198/D1198,"")
A1199: 2010 | B1199: facility_inpatient | C1199: 1400RU | D1199: 29 | E1199: 27 | F1199: 448000 | G1199: 2063 | J1199: =IF(D1199>0,F1199/D1199,"")
A1200: 2010 | B1200: facility_inpatient | C1200: 0507AB | D1200: 37 | E1200: 35 | F1200: 439600 | G1200: 2063 | H1200: REVIEW | I1200: HIGH_CLAIM_VOLUME | J1200: =IF(D1200>0,F1200/D1200,"")
A1201: 2010 | B1201: facility_inpatient | C1201: 4401DM | D1201: 48 | E1201: 45 | F1201: 439020 | G1201: 2063 | H1201: REVIEW | I1201: HIGH_CLAIM_VOLUME | J1201: =IF(D1201>0,F1201/D1201,"")
A1202: 2010 | B1202: facility_inpatient | C1202: 0600GH | D1202: 34 | E1202: 32 | F1202: 431000 | G1202: 2063 | H1202: REVIEW | I1202: HIGH_CLAIM_VOLUME | J1202: =IF(D1202>0,F1202/D1202,"")
A1203: 2010 | B1203: facility_inpatient | C1203: 3400SP | D1203: 45 | E1203: 42 | F1203: 425800 | G1203: 2063 | H1203: REVIEW | I1203: HIGH_CLAIM_VOLUME | J1203: =IF(D1203>0,F1203/D1203,"")
A1204: 2010 | B1204: facility_inpatient | C1204: 2100NQ | D1204: 43 | E1204: 40 | F1204: 425300 | G1204: 2063 | H1204: REVIEW | I1204: HIGH_CLAIM_VOLUME | J1204: =IF(D1204>0,F1204/D1204,"")
A1205: 2010 | B1205: facility_inpatient | C1205: 1501ZA | D1205: 33 | E1205: 32 | F1205: 417600 | G1205: 2063 | H1205: REVIEW | I1205: HIGH_CLAIM_VOLUME | J1205: =IF(D1205>0,F1205/D1205,"")
A1206: 2010 | B1206: facility_inpatient | C1206: 3902XB | D1206: 47 | E1206: 42 | F1206: 415000 | G1206: 2063 | H1206: REVIEW | I1206: HIGH_CLAIM_VOLUME | J1206: =IF(D1206>0,F1206/D1206,"")
A1207: 2010 | B1207: facility_inpatient | C1207: 0700JR | D1207: 45 | E1207: 42 | F1207: 400500 | G1207: 2063 | H1207: REVIEW | I1207: HIGH_CLAIM_VOLUME | J1207: =IF(D1207>0,F1207/D1207,"")
A1208: 2010 | B1208: facility_inpatient | C1208: 0505KQ | D1208: 42 | E1208: 41 | F1208: 398900 | G1208: 2063 | H1208: REVIEW | I1208: HIGH_CLAIM_VOLUME | J1208: =IF(D1208>0,F1208/D1208,"")
A1209: 2010 | B1209: facility_inpatient | C1209: 5130XG | D1209: 33 | E1209: 27 | F1209: 378000 | G1209: 2063 | H1209: REVIEW | I1209: HIGH_CLAIM_VOLUME | J1209: =IF(D1209>0,F1209/D1209,"")
A1210: 2010 | B1210: facility_inpatient | C1210: 4500NJ | D1210: 43 | E1210: 43 | F1210: 373500 | G1210: 2063 | H1210: REVIEW | I1210: HIGH_CLAIM_VOLUME | J1210: =IF(D1210>0,F1210/D1210,"")
A1211: 2010 | B1211: facility_inpatient | C1211: 1800WP | D1211: 29 | E1211: 27 | F1211: 370000 | G1211: 2063 | J1211: =IF(D1211>0,F1211/D1211,"")
A1212: 2010 | B1212: facility_inpatient | C1212: 1001NA | D1212: 39 | E1212: 36 | F1212: 365000 | G1212: 2063 | H1212: REVIEW | I1212: HIGH_CLAIM_VOLUME | J1212: =IF(D1212>0,F1212/D1212,"")
A1213: 2010 | B1213: facility_inpatient | C1213: 14018H | D1213: 37 | E1213: 36 | F1213: 362000 | G1213: 2063 | H1213: REVIEW | I1213: HIGH_CLAIM_VOLUME | J1213: =IF(D1213>0,F1213/D1213,"")
A1214: 2010 | B1214: facility_inpatient | C1214: 3302BQ | D1214: 41 | E1214: 41 | F1214: 359700 | G1214: 2063 | H1214: REVIEW | I1214: HIGH_CLAIM_VOLUME | J1214: =IF(D1214>0,F1214/D1214,"")
A1215: 2010 | B1215: facility_inpatient | C1215: 1002ZT | D1215: 42 | E1215: 42 | F1215: 359000 | G1215: 2063 | H1215: REVIEW | I1215: HIGH_CLAIM_VOLUME | J1215: =IF(D1215>0,F1215/D1215,"")
A1216: 2010 | B1216: facility_inpatient | C1216: 4900NA | D1216: 32 | E1216: 31 | F1216: 355500 | G1216: 2063 | H1216: REVIEW | I1216: HIGH_CLAIM_VOLUME | J1216: =IF(D1216>0,F1216/D1216,"")
A1217: 2010 | B1217: facility_inpatient | C1217: 3600TU | D1217: 37 | E1217: 32 | F1217: 353700 | G1217: 2063 | H1217: REVIEW | I1217: HIGH_CLAIM_VOLUME | J1217: =IF(D1217>0,F1217/D1217,"")
A1218: 2010 | B1218: facility_inpatient | C1218: 0300CC | D1218: 41 | E1218: 38 | F1218: 349400 | G1218: 2063 | H1218: REVIEW | I1218: HIGH_CLAIM_VOLUME | J1218: =IF(D1218>0,F1218/D1218,"")
A1219: 2010 | B1219: facility_inpatient | C1219: 05018N | D1219: 45 | E1219: 42 | F1219: 348000 | G1219: 2063 | H1219: REVIEW | I1219: HIGH_CLAIM_VOLUME | J1219: =IF(D1219>0,F1219/D1219,"")
A1220: 2010 | B1220: facility_inpatient | C1220: 1000AQ | D1220: 36 | E1220: 36 | F1220: 346000 | G1220: 2063 | H1220: REVIEW | I1220: HIGH_CLAIM_VOLUME | J1220: =IF(D1220>0,F1220/D1220,"")
A1221: 2010 | B1221: facility_inpatient | C1221: 36008A | D1221: 35 | E1221: 34 | F1221: 343000 | G1221: 2063 | H1221: REVIEW | I1221: HIGH_CLAIM_VOLUME | J1221: =IF(D1221>0,F1221/D1221,"")
A1222: 2010 | B1222: facility_inpatient | C1222: 3301KT | D1222: 32 | E1222: 30 | F1222: 340000 | G1222: 2063 | H1222: REVIEW | I1222: HIGH_CLAIM_VOLUME | J1222: =IF(D1222>0,F1222/D1222,"")
A1223: 2010 | B1223: facility_inpatient | C1223: 5001PC | D1223: 30 | E1223: 27 | F1223: 336000 | G1223: 2063 | H1223: REVIEW | I1223: HIGH_CLAIM_VOLUME | J1223: =IF(D1223>0,F1223/D1223,"")
... A1229: 2010 | B1229: facility_inpatient | C1229: 06018D | D1229: 36 | E1229: 34 | F1229: 320700 | G1229: 2063 | H1229: REVIEW | I1229: HIGH_CLAIM_VOLUME | J1229: =IF(D1229>0,F1229/D1229,"")
A1230: 2010 | B1230: facility_inpatient | C1230: 33008G | D1230: 19 | E1230: 17 | F1230: 317000 | G1230: 2063 | J1230: =IF(D1230>0,F1230/D1230,"")
A1231: 2010 | B1231: facility_inpatient | C1231: 0502VR | D1231: 32 | E1231: 32 | F1231: 315000 | G1231: 2063 | H1231: REVIEW | I1231: HIGH_CLAIM_VOLUME | J1231: =IF(D1231>0,F1231/D1231,"")
A1232: 2010 | B1232: facility_inpatient | C1232: 3600CS | D1232: 37 | E1232: 33 | F1232: 314000 | G1232: 2063 | H1232: REVIEW | I1232: HIGH_CLAIM_VOLUME | J1232: =IF(D1232>0,F1232/D1232,"")
A1233: 2010 | B1233: facility_inpatient | C1233: 33026U | D1233: 24 | E1233: 24 | F1233: 313000 | G1233: 2063 | J1233: =IF(D1233>0,F1233/D1233,"")
A1234: 2010 | B1234: facility_inpatient | C1234: 2200TM | D1234: 24 | E1234: 23 | F1234: 310000 | G1234: 2063 | J1234: =IF(D1234>0,F1234/D1234,"")
A1235: 2010 | B1235: facility_inpatient | C1235: 10016B | D1235: 27 | E1235: 23 | F1235: 305000 | G1235: 2063 | J1235: =IF(D1235>0,F1235/D1235,"")
A1236: 2010 | B1236: facility_inpatient | C1236: 1900AJ | D1236: 27 | E1236: 23 | F1236: 299000 | G1236: 2063 | J1236: =IF(D1236>0,F1236/D1236,"")
A1237: 2010 | B1237: facility_inpatient | C1237: 4400WA | D1237: 23 | E1237: 20 | F1237: 298000 | G1237: 2063 | J1237: =IF(D1237>0,F1237/D1237,"")
A1238: 2010 | B1238: facility_inpatient | C1238: 2100BM | D1238: 32 | E1238: 32 | F1238: 296000 | G1238: 2063 | H1238: REVIEW | I1238: HIGH_CLAIM_VOLUME | J1238: =IF(D1238>0,F1238/D1238,"")
A1239: 2010 | B1239: facility_inpatient | C1239: 0505YJ | D1239: 24 | E1239: 24 | F1239: 294700 | G1239: 2063 | J1239: =IF(D1239>0,F1239/D1239,"")
A1240: 2010 | B1240: facility_inpatient | C1240: 3302ND | D1240: 26 | E1240: 26 | F1240: 289000 | G1240: 2063 | J1240: =IF(D1240>0,F1240/D1240,"")
A1241: 2010 | B1241: facility_inpatient | C1241: 1300ZH | D1241: 25 | E1241: 21 | F1241: 288000 | G1241: 2063 | J1241: =IF(D1241>0,F1241/D1241,"")
A1242: 2010 | B1242: facility_inpatient | C1242: 1402CR | D1242: 30 | E1242: 29 | F1242: 288000 | G1242: 2063 | H1242: REVIEW | I1242: HIGH_CLAIM_VOLUME | J1242: =IF(D1242>0,F1242/D1242,"")
A1243: 2010 | B1243: facility_inpatient | C1243: 3400ZQ | D1243: 34 | E1243: 34 | F1243: 285000 | G1243: 2063 | H1243: REVIEW | I1243: HIGH_CLAIM_VOLUME | J1243: =IF(D1243>0,F1243/D1243,"")
A1244: 2010 | B1244: facility_inpatient | C1244: 31006K | D1244: 18 | E1244: 15 | F1244: 284900 | G1244: 2063 | J1244: =IF(D1244>0,F1244/D1244,"")
A1245: 2010 | B1245: facility_inpatient | C1245: 0502KN | D1245: 29 | E1245: 29 | F1245: 283700 | G1245: 2063 | J1245: =IF(D1245>0,F1245/D1245,"")
A1246: 2010 | B1246: facility_inpatient | C1246: 5000KV | D1246: 24 | E1246: 24 | F1246: 283100 | G1246: 2063 | J1246: =IF(D1246>0,F1246/D1246,"")
A1247: 2010 | B1247: facility_inpatient | C1247: 3302QQ | D1247: 23 | E1247: 21 | F1247: 281900 | G1247: 2063 | J1247: =IF(D1247>0,F1247/D1247,"")
A1248: 2010 | B1248: facility_inpatient | C1248: 5000PS | D1248: 33 | E1248: 33 | F1248: 279090 | G1248: 2063 | H1248: REVIEW | I1248: HIGH_CLAIM_VOLUME | J1248: =IF(D1248>0,F1248/D1248,"")
A1249: 2010 | B1249: facility_inpatient | C1249: 3100XU | D1249: 23 | E1249: 23 | F1249: 277000 | G1249: 2063 | J1249: =IF(D1249>0,F1249/D1249,"")
A1250: 2010 | B1250: facility_inpatient | C1250: 2600QH | D1250: 26 | E1250: 24 | F1250: 274000 | G1250: 2063 | J1250: =IF(D1250>0,F1250/D1250,"")
A1251: 2010 | B1251: facility_inpatient | C1251: 1002YC | D1251: 34 | E1251: 32 | F1251: 274000 | G1251: 2063 | H1251: REVIEW | I1251: HIGH_CLAIM_VOLUME | J1251: =IF(D1251>0,F1251/D1251,"")
A1252: 2010 | B1252: facility_inpatient | C1252: 5200GH | D1252: 29 | E1252: 29 | F1252: 271000 | G1252: 2063 | J1252: =IF(D1252>0,F1252/D1252,"")
A1253: 2010 | B1253: facility_inpatient | C1253: 3700JD | D1253: 27 | E1253: 24 | F1253: 270000 | G1253: 2063 | J1253: =IF(D1253>0,F1253/D1253,"")
A1254: 2010 | B1254: facility_inpatient | C1254: 2100ZH | D1254: 32 | E1254: 31 | F1254: 269100 | G1254: 2063 | H1254: REVIEW | I1254: HIGH_CLAIM_VOLUME | J1254: =IF(D1254>0,F1254/D1254,"")
A1255: 2010 | B1255: facility_inpatient | C1255: 0700QA | D1255: 32 | E1255: 27 | F1255: 269000 | G1255: 2063 | H1255: REVIEW | I1255: HIGH_CLAIM_VOLUME | J1255: =IF(D1255>0,F1255/D1255,"")
A1256: 2010 | B1256: facility_inpatient | C1256: 3303YT | D1256: 24 | E1256: 21 | F1256: 268500 | G1256: 2063 | J1256: =IF(D1256>0,F1256/D1256,"")
A1257: 2010 | B1257: facility_inpatient | C1257: 2200GD | D1257: 34 | E1257: 33 | F1257: 268000 | G1257: 2063 | H1257: REVIEW | I1257: HIGH_CLAIM_VOLUME | J1257: =IF(D1257>0,F1257/D1257,"")
A1258: 2010 | B1258: facility_inpatient | C1258: 2900UB | D1258: 23 | E1258: 21 | F1258: 268000 | G1258: 2063 | J1258: =IF(D1258>0,F1258/D1258,"")
A1259: 2010 | B1259: facility_inpatient | C1259: 1001WM | D1259: 25 | E1259: 23 | F1259: 267000 | G1259: 2063 | J1259: =IF(D1259>0,F1259/D1259,"")
A1260: 2010 | B1260: facility_inpatient | C1260: 2600GD | D1260: 24 | E1260: 21 | F1260: 266000 | G1260: 2063 | J1260: =IF(D1260>0,F1260/D1260,"")
A1261: 2010 | B1261: facility_inpatient | C1261: 3300JQ | D1261: 31 | E1261: 29 | F1261: 264000 | G1261: 2063 | H1261: REVIEW | I1261: HIGH_CLAIM_VOLUME | J1261: =IF(D1261>0,F1261/D1261,"")
A1262: 2010 | B1262: facility_inpatient | C1262: 0503NV | D1262: 35 | E1262: 31 | F1262: 263500 | G1262: 2063 | H1262: REVIEW | I1262: HIGH_CLAIM_VOLUME | J1262: =IF(D1262>0,F1262/D1262,"")
A1263: 2010 | B1263: facility_inpatient | C1263: 0300QR | D1263: 32 | E1263: 30 | F1263: 263000 | G1263: 2063 | H1263: REVIEW | I1263: HIGH_CLAIM_VOLUME | J1263: =IF(D1263>0,F1263/D1263,"")
A1264: 2010 | B1264: facility_inpatient | C1264: 41006B | D1264: 27 | E1264: 24 | F1264: 262000 | G1264: 2063 | J1264: =IF(D1264>0,F1264/D1264,"")
A1265: 2010 | B1265: facility_inpatient | C1265: 3700AC | D1265: 23 | E1265: 22 | F1265: 261000 | G1265: 2063 | J1265: =IF(D1265>0,F1265/D1265,"")
A1266: 2010 | B1266: facility_inpatient | C1266: 2501QH | D1266: 36 | E1266: 33 | F1266: 258500 | G1266: 2063 | H1266: REVIEW | I1266: HIGH_CLAIM_VOLUME | J1266: =IF(D1266>0,F1266/D1266,"")
A1267: 2010 | B1267: facility_inpatient | C1267: 15008B | D1267: 34 | E1267: 31 | F1267: 258000 | G1267: 2063 | H1267: REVIEW | I1267: HIGH_CLAIM_VOLUME | J1267: =IF(D1267>0,F1267/D1267,"")
A1268: 2010 | B1268: facility_inpatient | C1268: 0500VS | D1268: 30 | E1268: 26 | F1268: 254000 | G1268: 2063 | H1268: REVIEW | I1268: HIGH_CLAIM_VOLUME | J1268: =IF(D1268>0,F1268/D1268,"")
A1269: 2010 | B1269: facility_inpatient | C1269: 1800AD | D1269: 31 | E1269: 29 | F1269: 247000 | G1269: 2063 | H1269: REVIEW | I1269: HIGH_CLAIM_VOLUME | J1269: =IF(D1269>0,F1269/D1269,"")
A1270: 2010 | B1270: facility_inpatient | C1270: 4500PK | D1270: 31 | E1270: 31 | F1270: 239700 | G1270: 2063 | H1270: REVIEW | I1270: HIGH_CLAIM_VOLUME | J1270: =IF(D1270>0,F1270/D1270,"")
A1271: 2010 | B1271: facility_outpatient | C1271: 0502NA | D1271: 2228 | E1271: 1017 | F1271: 603370 | G1271: 5723 | H1271: REVIEW | I1271: HIGH_CLAIM_VOLUME | J1271: =IF(D1271>0,F1271/D1271,"")
A1272: 2010 | B1272: facility_outpatient | C1272: 2201DT | D1272: 1298 | E1272: 678 | F1272: 410660 | G1272: 5723 | H1272: REVIEW | I1272: HIGH_CLAIM_VOLUME | J1272: =IF(D1272>0,F1272/D1272,"")
A1273: 2010 | B1273: facility_outpatient | C1273: 0505TK | D1273: 1257 | E1273: 557 | F1273: 371780 | G1273: 5723 | H1273: REVIEW | I1273: HIGH_CLAIM_VOLUME | J1273: =IF(D1273>0,F1273/D1273,"")
A1274: 2010 | B1274: facility_outpatient | C1274: 3400ZQ | D1274: 853 | E1274: 713 | F1274: 275080 | G1274: 5723 | H1274: REVIEW | I1274: HIGH_CLAIM_VOLUME | J1274: =IF(D1274>0,F1274/D1274,"")
A1275: 2010 | B1275: facility_outpatient | C1275: 2301GU | D1275: 961 | E1275: 550 | F1275: 258840 | G1275: 5723 | H1275: REVIEW | I1275: HIGH_CLAIM_VOLUME | J1275: =IF(D1275>0,F1275/D1275,"")
A1276: 2010 | B1276: facility_outpatient | C1276: 4500NJ | D1276: 760 | E1276: 635 | F1276: 249850 | G1276: 5723 | H1276: REVIEW | I1276: HIGH_CLAIM_VOLUME | J1276: =IF(D1276>0,F1276/D1276,"")
A1277: 2010 | B1277: facility_outpatient | C1277: 3300KJ | D1277: 831 | E1277: 455 | F1277: 248730 | G1277: 5723 | H1277: REVIEW | I1277: HIGH_CLAIM_VOLUME | J1277: =IF(D1277>0,F1277/D1277,"")
... A5652: 2010 | B5652: professional_npi | C5652: 2192040571 | D5652: 92 | E5652: 92 | F5652: 7150 | G5652: 375944 | H5652: REVIEW | I5652: HIGH_CLAIM_VOLUME | J5652: =IF(D5652>0,F5652/D5652,"")
A5653: 2010 | B5653: professional_npi | C5653: 0462215198 | D5653: 7 | E5653: 7 | F5653: 7110 | G5653: 375944 | J5653: =IF(D5653>0,F5653/D5653,"")
A5654: 2010 | B5654: professional_npi | C5654: 6858055920 | D5654: 84 | E5654: 82 | F5654: 7100 | G5654: 375944 | H5654: REVIEW | I5654: HIGH_CLAIM_VOLUME | J5654: =IF(D5654>0,F5654/D5654,"")
A5655: 2010 | B5655: professional_npi | C5655: 1913173958 | D5655: 83 | E5655: 77 | F5655: 7080 | G5655: 375944 | H5655: REVIEW | I5655: HIGH_CLAIM_VOLUME | J5655: =IF(D5655>0,F5655/D5655,"")
A5656: 2010 | B5656: professional_npi | C5656: 8774379826 | D5656: 78 | E5656: 76 | F5656: 7020 | G5656: 375944 | H5656: REVIEW | I5656: HIGH_CLAIM_VOLUME | J5656: =IF(D5656>0,F5656/D5656,"")
A5657: 2010 | B5657: professional_npi | C5657: 7219590538 | D5657: 101 | E5657: 39 | F5657: 7000 | G5657: 375944 | H5657: REVIEW | I5657: HIGH_CLAIM_VOLUME | J5657: =IF(D5657>0,F5657/D5657,"")
A5658: 2010 | B5658: professional_npi | C5658: 1358024404 | D5658: 64 | E5658: 64 | F5658: 6990 | G5658: 375944 | H5658: REVIEW | I5658: HIGH_CLAIM_VOLUME | J5658: =IF(D5658>0,F5658/D5658,"")
A5659: 2010 | B5659: professional_npi | C5659: 2687228379 | D5659: 96 | E5659: 96 | F5659: 6980 | G5659: 375944 | H5659: REVIEW | I5659: HIGH_CLAIM_VOLUME | J5659: =IF(D5659>0,F5659/D5659,"")
A5660: 2010 | B5660: professional_npi | C5660: 1194614838 | D5660: 95 | E5660: 73 | F5660: 6930 | G5660: 375944 | H5660: REVIEW | I5660: HIGH_CLAIM_VOLUME | J5660: =IF(D5660>0,F5660/D5660,"")
...

Sheet Readmission_Review
A1: CMS synthetic claims - not real patient or provider performance.
A2: 30-day readmission proxy by year and utilization risk tier
A3: Measure-inspired proxy, not a certified measure. Rate is a formula: readmitted / eligible index stays.
A4: Year | B4: Utilization_risk_tier | C4: Eligible_index_stays | D4: Readmitted_stays | E4: Excluded_died_in_stay | F4: Excluded_insufficient_followup | G4: Stays_considered | H4: Readmission_rate
A5: 2008 | B5: not_assessed | C5: 25861 | D5: 3906 | E5: 1 | F5: 0 | G5: 25862 | H5: =IF(C5>0,D5/C5,"")
A6: 2009 | B6: high | C6: 10737 | D6: 1108 | E6: 2 | F6: 0 | G6: 10739 | H6: =IF(C6>0,D6/C6,"")
A7: 2009 | B7: low | C7: 4958 | D7: 202 | E7: 0 | F7: 0 | G7: 4958 | H7: =IF(C7>0,D7/C7,"")
A8: 2009 | B8: medium | C8: 9068 | D8: 556 | E8: 0 | F8: 0 | G8: 9068 | H8: =IF(C8>0,D8/C8,"")
A9: 2010 | B9: high | C9: 4942 | D9: 304 | E9: 0 | F9: 194 | G9: 5136 | H9: =IF(C9>0,D9/C9,"")
A10: 2010 | B10: low | C10: 2695 | D10: 58 | E10: 1 | F10: 31 | G10: 2727 | H10: =IF(C10>0,D10/C10,"")
A11: 2010 | B11: medium | C11: 5784 | D11: 215 | E11: 0 | F11: 85 | G11: 5869 | H11: =IF(C11>0,D11/C11,"")

Sheet Member_Risk_Tiers
A1: CMS synthetic claims - not real patient or provider performance.
A2: Utilization risk tiers (descriptive stratification)
A3: Not CMS-HCC, RAF or official risk adjustment. Tier uses prior-year information only. Aggregates only, no beneficiary rows.
A4: Year | B4: Utilization_risk_tier | C4: Beneficiaries | D4: Member_years | E4: Payment_amount | F4: Admissions | G4: Payment_per_beneficiary | H4: Admissions_per_1000_member_years
A5: 2008 | B5: not_assessed | C5: 116352 | D5: 107296.75 | E5: 483275670 | F5: 26262 | G5: =IF(C5>0,E5/C5,"") | H5: =IF(D5>0,F5/D5*1000,"")
A6: 2009 | B6: high | C6: 20033 | D6: 19805.417 | E6: 215495080 | F6: 10455 | G6: =IF(C6>0,E6/C6,"") | H6: =IF(D6>0,F6/D6*1000,"")
A7: 2009 | B7: low | C7: 63349 | D7: 55725.167 | E7: 101967960 | F7: 5046 | G7: =IF(C7>0,E7/C7,"") | H7: =IF(D7>0,F7/D7*1000,"")
A8: 2009 | B8: medium | C8: 31156 | D8: 30821.583 | E8: 187338460 | F8: 9209 | G8: =IF(C8>0,E8/C8,"") | H8: =IF(D8>0,F8/D8*1000,"")
A9: 2010 | B9: high | C9: 25386 | D9: 25003.25 | E9: 115141480 | F9: 4796 | G9: =IF(C9>0,E9/C9,"") | H9: =IF(D9>0,F9/D9*1000,"")
A10: 2010 | B10: low | C10: 52546 | D10: 45073.583 | E10: 51548060 | F10: 2727 | G10: =IF(C10>0,E10/C10,"") | H10: =IF(D10>0,F10/D10*1000,"")
A11: 2010 | B11: medium | C11: 34822 | D11: 34330.583 | E11: 120022520 | F11: 5864 | G11: =IF(C11>0,E11/C11,"") | H11: =IF(D11>0,F11/D11*1000,"")

Sheet Data_Quality
A1: CMS synthetic claims - not real patient or provider performance.
A2: Data quality
A3: Counts from the pipeline. Duplicates, impossible dates and out-of-window claims are excluded from metrics and reported here.
A4: Check | B4: Setting | C4: Value
A5: Exact duplicate rows dropped | B5: inpatient | C5: 0
A6: Exact duplicate rows dropped | B6: outpatient | C6: 0
A7: Exact duplicate rows dropped | B7: carrier | C7: 0
A8: Impossible or missing dates | B8: inpatient | C8: 0
A9: Impossible or missing dates | B9: outpatient | C9: 278
A10: Impossible or missing dates | B10: carrier | C10: 0
A11: Outside study window | B11: inpatient | C11: 226
A12: Outside study window | B12: outpatient | C12: 312
A13: Outside study window | B13: carrier | C13: 0
A14: Negative payment claims | B14: inpatient | C14: 55
A15: Negative payment claims | B15: outpatient | C15: 2557
A16: Negative payment claims | B16: carrier | C16: 0
... A25: Orphan claims (beneficiary missing) | B25: all | C25: 0

Sheet Metric_Dictionary
A1: CMS synthetic claims - not real patient or provider performance.
A2: Metric dictionary
A3: Single source: config/metric_dictionary.yml.
A4: Metric | B4: Category | C4: Definition | D4: Numerator | E4: Denominator | F4: Exclusions | G4: Unit | H4: Source_fields | I4: Caveat
A5: Beneficiaries | B5: Population | C5: Synthetic beneficiaries with a row in the year's beneficiary summary file. | D5: Count of beneficiary-year rows | E5: n/a | F5: none | G5: beneficiaries | H5: DESYNPUF_ID (beneficiary summary) | I5: Synthetic people. DE-SynPUF is a 5 percent synthetic sample of 2008 beneficiaries.
A6: Member months | B6: Population | C6: Months a beneficiary contributes to rates. A beneficiary-year contributes min(Part A coverage months, months alive in the year), placed from January. | D6: Sum over beneficiary-years of min(BENE_HI_CVRAGE_TOT_MONS, months alive) | E6: n/a | F6: Deceased beneficiaries stop after the month of BENE_DEATH_DT | G6: member months | H6: BENE_HI_CVRAGE_TOT_MONS, BENE_DEATH_DT | I6: CMS gives a count of covered months, not which months. Placing them from January is an assumption.
A7: Claims per 1,000 member-years | B7: Utilization | C7: Analytic claims divided by member years, times 1,000. | D7: Analytic claims (beneficiary + CLM_ID within a setting, segments merged) | E7: Member months divided by 12 | F7: Claims with invalid dates, claims dated outside 2008-01-01 to 2010-12-31, duplicate rows | G7: claims per 1,000 member-years | H7: DESYNPUF_ID, CLM_ID, CLM_FROM_DT, CLM_THRU_DT, SEGMENT | I7: Inpatient claims are dated by admission date.
A8: Inpatient admissions per 1,000 member-years | B8: Utilization | C8: Continuous inpatient stays per 1,000 member-years. A claim admitted on or before the discharge date of the beneficiary's earlier stay continues that stay. | D8: Inpatient stays by admission date | E8: Member years | F8: Invalid or out-of-window inpatient claims | G8: admissions per 1,000 member-years | H8: CLM_ADMSN_DT, NCH_BENE_DSCHRG_DT, CLM_FROM_DT, CLM_THRU_DT | I8: Transfers are merged; no discharge status field exists to identify them directly.
A9: ED visit proxy per 1,000 member-years | B9: Utilization | C9: Outpatient claims carrying at least one HCPCS code from 99281 to 99285, per 1,000 member-years. | D9: Analytic outpatient claims with an ED evaluation and management code | E9: Member years | F9: none beyond analytic-claim rules | G9: ED proxy visits per 1,000 member-years | H9: HCPCS_CD_1 to HCPCS_CD_45 (outpatient) | I9: DE-SynPUF has no revenue center codes, so this is a code-based proxy, not a validated ED measure.
A10: Outpatient visits per 1,000 member-years | B10: Utilization | C10: Analytic outpatient claims per 1,000 member-years. | D10: Analytic outpatient claims | E10: Member years | F10: analytic-claim rules | G10: claims per 1,000 member-years | H10: outpatient claims file | I10: A claim is not necessarily a distinct visit.
A11: Carrier service lines | B11: Utilization | C11: Carrier line items (up to 13 per claim) that have a HCPCS code, a non-zero payment or a performing NPI. CMS pads unused slots with a 0.00 payment; those padded slots are not lines. | D11: Analytic carrier lines | E11: n/a | F11: analytic-claim rules | G11: lines | H11: HCPCS_CD_1..13, LINE_NCH_PMT_AMT_1..13, PRF_PHYSN_NPI_1..13 | I11: Line-level payment is the only carrier payment field.
A12: Total claim payment amount | B12: Payment | C12: Medicare trust fund payment on analytic claims. Institutional claims use CLM_PMT_AMT (segments summed); carrier claims use LINE_NCH_PMT_AMT_1..13 (lines summed). Negative amounts are payment adjustments and are included. | D12: Sum of payment on analytic claims | E12: n/a | F12: Invalid-date and out-of-window claims are reported separately | G12: US dollars (synthetic) | H12: CLM_PMT_AMT, LINE_NCH_PMT_AMT_1..13 | I12: Not a cost, charge or allowed amount. Beneficiary summary MEDREIMB_* fields do not tie to claim payments and are not used.
A13: Payment per beneficiary | B13: Payment | C13: Total claim payment amount divided by beneficiaries in the year. | D13: Total claim payment amount | E13: Beneficiary summary rows in the year | F13: analytic-claim rules | G13: US dollars per beneficiary (synthetic) | H13: CLM_PMT_AMT, LINE_NCH_PMT_AMT_1..13 | I13: Includes beneficiaries with no claims.
A14: Payment per admission | B14: Payment | C14: Inpatient payment divided by inpatient stays. | D14: Inpatient CLM_PMT_AMT on analytic claims | E14: Inpatient stays by admission year | F14: analytic-claim rules | G14: US dollars per admission (synthetic) | H14: CLM_PMT_AMT | I14: Payment on a claim dated by admission is attributed to the admission year.
A15: Payment concentration (top 5 percent) | B15: Payment | C15: Share of a year's payment held by the highest-paid ceil(5 percent of beneficiaries) beneficiaries. | D15: Payment of the top ceil(5 percent x N) beneficiaries | E15: Total payment in the year | F15: none | G15: share | H15: CLM_PMT_AMT, LINE_NCH_PMT_AMT_1..13 | I15: Ties are broken by beneficiary ID.
... A19: Provider review flag | B19: Provider operations | C19: A provider-year whose payment per claim or claim volume exceeds Q3 plus a multiple (default 3, Tukey far-out fence) of the interquartile range of its peers (same provider type, setting for facilities, and year), with a minimum claim count and peer count. The fence applies only when peers vary (IQR above zero). | D19: n/a | E19: n/a | F19: Groups with too few peers or claims, or with no spread among peers, are not flagged | G19: flag with reason codes | H19: PRVDR_NUM, PRF_PHYSN_NPI_1..13 | I19: A prompt for review only. It is not evidence of fraud, poor quality or provider performance.

Sheet Reconciliation
A1: CMS synthetic claims - not real patient or provider performance.
A2: Reconciliation: workbook totals versus DuckDB
A3: Workbook column: a formula over this workbook's own tables. DuckDB column: value read from the marts. Tolerance: half a cent for money, zero for counts.
A4: Check | B4: DuckDB | C4: Tolerance | D4: Workbook_value | E4: Variance | F4: Status
A5: Monthly claims (all settings) | B5: 5587039 | C5: 0 | D5: =SUM(Monthly_Utilization!E5:E112) | E5: =ABS(D5-B5) | F5: =IF(E5<=C5,"PASS","FAIL")
A6: Monthly admissions | B6: 64359 | C6: 0 | D6: =SUM(Monthly_Utilization!G5:G112) | E6: =ABS(D6-B6) | F6: =IF(E6<=C6,"PASS","FAIL")
A7: Monthly ED proxy visits | B7: 62581 | C7: 0 | D7: =SUM(Monthly_Utilization!H5:H112) | E7: =ABS(D7-B7) | F7: =IF(E7<=C7,"PASS","FAIL")
A8: Monthly paid amount | B8: 1274789230 | C8: 0.005 | D8: =SUM(Monthly_Payments!F5:F112) | E8: =ABS(D8-B8) | F8: =IF(E8<=C8,"PASS","FAIL")
A9: Monthly payment claims | B9: 5587039 | C9: 0 | D9: =SUM(Monthly_Payments!E5:E112) | E9: =ABS(D9-B9) | F9: =IF(E9<=C9,"PASS","FAIL")
A10: Executive: claims | B10: 5587039 | C10: 0 | D10: =SUM(Executive_Summary!D5:D7) | E10: =ABS(D10-B10) | F10: =IF(E10<=C10,"PASS","FAIL")
A11: Executive: paid amount | B11: 1274789230 | C11: 0.005 | D11: =SUM(Executive_Summary!E5:E7) | E11: =ABS(D11-B11) | F11: =IF(E11<=C11,"PASS","FAIL")
A12: Executive: admissions | B12: 64359 | C12: 0 | D12: =SUM(Executive_Summary!F5:F7) | E12: =ABS(D12-B12) | F12: =IF(E12<=C12,"PASS","FAIL")
A13: Executive: member years x 12 | B13: 3816676 | C13: 1e-06 | D13: =SUM(Executive_Summary!C5:C7)*12 | E13: =ABS(D13-B13) | F13: =IF(E13<=C13,"PASS","FAIL")
A14: Readmission stays considered | B14: 64359 | C14: 0 | D14: =SUM(Readmission_Review!G5:G11) | E14: =ABS(D14-B14) | F14: =IF(E14<=C14,"PASS","FAIL")
A16: Overall | B16: =IF(COUNTIF(F5:F14,"FAIL")=0,"ALL CHECKS PASS","REVIEW")
